AUTHORS
CHANGELOG
LICENSE
MANIFEST.in
README.rst
cuda_build.py
setup.py
miga/Population.pxd
miga/__init__.py
miga/miga.cpp
miga/miga.pyx
miga/types.pxd
miga.egg-info/PKG-INFO
miga.egg-info/SOURCES.txt
miga.egg-info/dependency_links.txt
miga.egg-info/requires.txt
miga.egg-info/top_level.txt
miga/src/CPUPopulation.cpp
miga/src/CPUPopulation.hpp
miga/src/GPUPopulation.cu
miga/src/GPUPopulation.hpp
miga/src/Population.cpp
miga/src/Population.hpp
miga/src/SimpleGPUPopulation.cu
miga/src/SimpleGPUPopulation.hpp
miga/src/cuda_tools.cuh
miga/src/types.h
third-party/cub/.cproject
third-party/cub/.git
third-party/cub/.project
third-party/cub/CHANGE_LOG.TXT
third-party/cub/LICENSE.TXT
third-party/cub/README.md
third-party/cub/common.mk
third-party/cub/eclipse code style profile.xml
third-party/cub/.settings/.gitignore
third-party/cub/.settings/org.eclipse.cdt.codan.core.prefs
third-party/cub/.settings/org.eclipse.cdt.core.prefs
third-party/cub/.settings/org.eclipse.cdt.ui.prefs
third-party/cub/.settings/org.eclipse.core.runtime.prefs
third-party/cub/cub/cub.cuh
third-party/cub/cub/util_allocator.cuh
third-party/cub/cub/util_arch.cuh
third-party/cub/cub/util_debug.cuh
third-party/cub/cub/util_device.cuh
third-party/cub/cub/util_macro.cuh
third-party/cub/cub/util_namespace.cuh
third-party/cub/cub/util_ptx.cuh
third-party/cub/cub/util_type.cuh
third-party/cub/cub/agent/agent_histogram.cuh
third-party/cub/cub/agent/agent_radix_sort_downsweep.cuh
third-party/cub/cub/agent/agent_radix_sort_upsweep.cuh
third-party/cub/cub/agent/agent_reduce.cuh
third-party/cub/cub/agent/agent_reduce_by_key.cuh
third-party/cub/cub/agent/agent_rle.cuh
third-party/cub/cub/agent/agent_scan.cuh
third-party/cub/cub/agent/agent_segment_fixup.cuh
third-party/cub/cub/agent/agent_select_if.cuh
third-party/cub/cub/agent/agent_spmv_orig.cuh
third-party/cub/cub/agent/single_pass_scan_operators.cuh
third-party/cub/cub/block/block_adjacent_difference.cuh
third-party/cub/cub/block/block_discontinuity.cuh
third-party/cub/cub/block/block_exchange.cuh
third-party/cub/cub/block/block_histogram.cuh
third-party/cub/cub/block/block_load.cuh
