Metadata-Version: 2.1
Name: miga
Version: 1.0.0
Summary: Python package to optimize mutual information between two multiple sequence alignment.
Home-page: https://github.com/caioss/miga
Author: Caio S. Souza
Author-email: caiobiounb@gmail.com
License: LGPLv3+
Project-URL: Documentation, https://miga.readthedocs.io/
Project-URL: Source, https://github.com/caioss/miga/
Project-URL: Tracker, https://github.com/caioss/miga/issues/
Keywords: mutual information,sequence alignment,cuda,GPU,genetic algorithm
Platform: UNKNOWN
Classifier: Development Status :: 5 - Production/Stable
Classifier: Intended Audience :: Science/Research
Classifier: Topic :: Scientific/Engineering :: Bio-Informatics
Classifier: License :: OSI Approved :: GNU Lesser General Public License v3 or later (LGPLv3+)
Classifier: Programming Language :: Python :: 2.7
Classifier: Programming Language :: Python :: 3
Classifier: Programming Language :: C++
Classifier: Programming Language :: Cython
Classifier: Natural Language :: English
Classifier: Operating System :: POSIX :: Linux
